{
    "NUM_Tau3MuTracker_DEN_genTracks": {
        "pt_abseta": {
            "binning": [
                {
                    "binning": [
                        1.2,
                        1.5,
                        2.0,
                        2.5,
                        2.75,
                        3.0,
                        3.25,
                        3.5,
                        3.75,
                        4.0,
                        4.5,
                        5.0,
                        6.0,
                        8.0,
                        10.0,
                        15.0,
                        20.0,
                        30.0,
                        40.0
                    ],
                    "variable": "pt"
                },
                {
                    "binning": [
                        0.0,
                        0.9,
                        1.2,
                        2.1,
                        2.4
                    ],
                    "variable": "abseta"
                }
            ],
            "pt:[1.2,1.5]": {
                "abseta:[0.0,0.9]": {
                    "stat": 0.0,
                    "syst": 0.0,
                    "value": 1.0
                },
                "abseta:[0.9,1.2]": {
                    "stat": 0.0,
                    "syst": 0.0,
                    "value": 1.0
                },
                "abseta:[1.2,2.1]": {
                    "stat": 0.07909164583163993,
                    "syst": 0.0,
                    "value": 1.0221254051776498
                },
                "abseta:[2.1,2.4]": {
                    "stat": 0.11371741499089433,
                    "syst": 0.0,
                    "value": 1.4476455734347928
                }
            },
            "pt:[1.5,2.0]": {
                "abseta:[0.0,0.9]": {
                    "stat": 0.0,
                    "syst": 0.0,
                    "value": 1.0
                },
                "abseta:[0.9,1.2]": {
                    "stat": 0.0,
                    "syst": 0.0,
                    "value": 1.0
                },
                "abseta:[1.2,2.1]": {
                    "stat": 0.05690501312431612,
                    "syst": 0.0,
                    "value": 1.014494849592318
                },
                "abseta:[2.1,2.4]": {
                    "stat": 0.28675714398133517,
                    "syst": 0.0,
                    "value": 2.5543353514572407
                }
            },
            "pt:[10.0,15.0]": {
                "abseta:[0.0,0.9]": {
                    "stat": 0.1410218726756283,
                    "syst": 0.0,
                    "value": 1.524433497473158
                },
                "abseta:[0.9,1.2]": {
                    "stat": 0.24563404165434577,
                    "syst": 0.0,
                    "value": 2.2781484214175265
                },
                "abseta:[1.2,2.1]": {
                    "stat": 0.17555331263260207,
                    "syst": 0.0,
                    "value": 2.105405273363217
                },
                "abseta:[2.1,2.4]": {
                    "stat": 1.2032060187414433,
                    "syst": 0.0,
                    "value": 6.813965541979397
                }
            },
            "pt:[15.0,20.0]": {
                "abseta:[0.0,0.9]": {
                    "stat": 0.1538057737857184,
                    "syst": 0.0,
                    "value": 1.6067135191488
                },
                "abseta:[0.9,1.2]": {
                    "stat": 0.31919517261473723,
                    "syst": 0.0,
                    "value": 1.914265213335704
                },
                "abseta:[1.2,2.1]": {
                    "stat": 0.2037829299246775,
                    "syst": 0.0,
                    "value": 1.8807743609371133
                },
                "abseta:[2.1,2.4]": {
                    "stat": 1.6681797667267706,
                    "syst": 0.0,
                    "value": 5.77034208418304
                }
            },
            "pt:[2.0,2.5]": {
                "abseta:[0.0,0.9]": {
                    "stat": 0.0,
                    "syst": 0.0,
                    "value": 1.0
                },
                "abseta:[0.9,1.2]": {
                    "stat": 0.0,
                    "syst": 0.0,
                    "value": 1.0
                },
                "abseta:[1.2,2.1]": {
                    "stat": 0.06711468278297286,
                    "syst": 0.0,
                    "value": 1.0460980121844974
                },
                "abseta:[2.1,2.4]": {
                    "stat": 0.43328892376591666,
                    "syst": 0.0,
                    "value": 1.231502479649949
                }
            },
            "pt:[2.5,2.75]": {
                "abseta:[0.0,0.9]": {
                    "stat": 0.0,
                    "syst": 0.0,
                    "value": 1.0
                },
                "abseta:[0.9,1.2]": {
                    "stat": 0.0,
                    "syst": 0.0,
                    "value": 1.0
                },
                "abseta:[1.2,2.1]": {
                    "stat": 0.13476832354103754,
                    "syst": 0.0,
                    "value": 1.1911657665000346
                },
                "abseta:[2.1,2.4]": {
                    "stat": 0.7254979392142893,
                    "syst": 0.0,
                    "value": 3.1054894896909975
                }
            },
            "pt:[2.75,3.0]": {
                "abseta:[0.0,0.9]": {
                    "stat": 0.0,
                    "syst": 0.0,
                    "value": 1.0
                },
                "abseta:[0.9,1.2]": {
                    "stat": 0.0,
                    "syst": 0.0,
                    "value": 1.0
                },
                "abseta:[1.2,2.1]": {
                    "stat": 0.16187533657933717,
                    "syst": 0.0,
                    "value": 1.3275670385259486
                },
                "abseta:[2.1,2.4]": {
                    "stat": 1.0079859646939338,
                    "syst": 0.0,
                    "value": 2.8311835687485383
                }
            },
            "pt:[20.0,30.0]": {
                "abseta:[0.0,0.9]": {
                    "stat": 0.16055240666384818,
                    "syst": 0.0,
                    "value": 1.3316966215830064
                },
                "abseta:[0.9,1.2]": {
                    "stat": 0.21962716293805415,
                    "syst": 0.0,
                    "value": 1.251408015884356
                },
                "abseta:[1.2,2.1]": {
                    "stat": 0.1874932442929959,
                    "syst": 0.0,
                    "value": 1.8403918249105737
                },
                "abseta:[2.1,2.4]": {
                    "stat": 0.2552909209988396,
                    "syst": 0.0,
                    "value": 1.9837907323366017
                }
            },
            "pt:[3.0,3.25]": {
                "abseta:[0.0,0.9]": {
                    "stat": 0.0,
                    "syst": 0.0,
                    "value": 1.0
                },
                "abseta:[0.9,1.2]": {
                    "stat": 0.0,
                    "syst": 0.0,
                    "value": 1.0
                },
                "abseta:[1.2,2.1]": {
                    "stat": 0.20009587718559543,
                    "syst": 0.0,
                    "value": 1.3848893071625694
                },
                "abseta:[2.1,2.4]": {
                    "stat": 0.48795163756706944,
                    "syst": 0.0,
                    "value": 2.174683634390158
                }
            },
            "pt:[3.25,3.5]": {
                "abseta:[0.0,0.9]": {
                    "stat": 0.0,
                    "syst": 0.0,
                    "value": 1.0
                },
                "abseta:[0.9,1.2]": {
                    "stat": 0.0,
                    "syst": 0.0,
                    "value": 1.0
                },
                "abseta:[1.2,2.1]": {
                    "stat": 0.21405214918062884,
                    "syst": 0.0,
                    "value": 0.8532957692611951
                },
                "abseta:[2.1,2.4]": {
                    "stat": 1.32332071333195,
                    "syst": 0.0,
                    "value": 4.223878445069525
                }
            },
            "pt:[3.5,3.75]": {
                "abseta:[0.0,0.9]": {
                    "stat": 0.09294094059396851,
                    "syst": 0.0,
                    "value": 0.8682466902715292
                },
                "abseta:[0.9,1.2]": {
                    "stat": 0.13609729724908598,
                    "syst": 0.0,
                    "value": 0.743197072733158
                },
                "abseta:[1.2,2.1]": {
                    "stat": 0.27346044928824875,
                    "syst": 0.0,
                    "value": 1.2176373242849743
                },
                "abseta:[2.1,2.4]": {
                    "stat": 0.645778554581922,
                    "syst": 0.0,
                    "value": 0.7512696706608338
                }
            },
            "pt:[3.75,4.0]": {
                "abseta:[0.0,0.9]": {
                    "stat": 0.13377638538391357,
                    "syst": 0.0,
                    "value": 1.2272528001470575
                },
                "abseta:[0.9,1.2]": {
                    "stat": 0.18971970528406393,
                    "syst": 0.0,
                    "value": 0.8755518133314216
                },
                "abseta:[1.2,2.1]": {
                    "stat": 0.31055026373741357,
                    "syst": 0.0,
                    "value": 1.2544247259113581
                },
                "abseta:[2.1,2.4]": {
                    "stat": 0.773073971183988,
                    "syst": 0.0,
                    "value": 3.068351271598943
                }
            },
            "pt:[30.0,40.0]": {
                "abseta:[0.0,0.9]": {
                    "stat": 0.19966401932266023,
                    "syst": 0.0,
                    "value": 1.4166185422917772
                },
                "abseta:[0.9,1.2]": {
                    "stat": 0.3061113114970692,
                    "syst": 0.0,
                    "value": 1.0614114105419072
                },
                "abseta:[1.2,2.1]": {
                    "stat": 0.2438283785539833,
                    "syst": 0.0,
                    "value": 1.706132544181028
                },
                "abseta:[2.1,2.4]": {
                    "stat": 1.0173198231591192,
                    "syst": 0.0,
                    "value": 2.307825285955474
                }
            },
            "pt:[4.0,4.5]": {
                "abseta:[0.0,0.9]": {
                    "stat": 0.1348893850825947,
                    "syst": 0.0,
                    "value": 1.3241597416193864
                },
                "abseta:[0.9,1.2]": {
                    "stat": 0.2332970516660373,
                    "syst": 0.0,
                    "value": 1.3243813834493252
                },
                "abseta:[1.2,2.1]": {
                    "stat": 0.1987062150943565,
                    "syst": 0.0,
                    "value": 1.2217365015551447
                },
                "abseta:[2.1,2.4]": {
                    "stat": 0.5137546898588483,
                    "syst": 0.0,
                    "value": 2.0062647398331017
                }
            },
            "pt:[4.5,5.0]": {
                "abseta:[0.0,0.9]": {
                    "stat": 0.19115052956924758,
                    "syst": 0.0,
                    "value": 1.2769619798244625
                },
                "abseta:[0.9,1.2]": {
                    "stat": 0.5620915984817791,
                    "syst": 0.0,
                    "value": 1.985977611435972
                },
                "abseta:[1.2,2.1]": {
                    "stat": 0.24077878559044538,
                    "syst": 0.0,
                    "value": 1.5405846687993907
                },
                "abseta:[2.1,2.4]": {
                    "stat": 0.7362936445381776,
                    "syst": 0.0,
                    "value": 2.3405034957592843
                }
            },
            "pt:[5.0,6.0]": {
                "abseta:[0.0,0.9]": {
                    "stat": 0.2607764486328878,
                    "syst": 0.0,
                    "value": 1.8882386212050442
                },
                "abseta:[0.9,1.2]": {
                    "stat": 0.6586569585687492,
                    "syst": 0.0,
                    "value": 1.8752362538634173
                },
                "abseta:[1.2,2.1]": {
                    "stat": 0.2256401070952197,
                    "syst": 0.0,
                    "value": 1.5653652806470113
                },
                "abseta:[2.1,2.4]": {
                    "stat": 0.9163180692093361,
                    "syst": 0.0,
                    "value": 2.8447187158497047
                }
            },
            "pt:[6.0,8.0]": {
                "abseta:[0.0,0.9]": {
                    "stat": 0.18302914851998783,
                    "syst": 0.0,
                    "value": 1.2409519253791574
                },
                "abseta:[0.9,1.2]": {
                    "stat": 0.36427806632987214,
                    "syst": 0.0,
                    "value": 1.595731403978715
                },
                "abseta:[1.2,2.1]": {
                    "stat": 0.18476898129884095,
                    "syst": 0.0,
                    "value": 1.7271183864606343
                },
                "abseta:[2.1,2.4]": {
                    "stat": 0.6126740757985806,
                    "syst": 0.0,
                    "value": 2.761896848617348
                }
            },
            "pt:[8.0,10.0]": {
                "abseta:[0.0,0.9]": {
                    "stat": 0.19324375150836734,
                    "syst": 0.0,
                    "value": 1.3258702609833184
                },
                "abseta:[0.9,1.2]": {
                    "stat": 0.2813658045053371,
                    "syst": 0.0,
                    "value": 2.2223159475675414
                },
                "abseta:[1.2,2.1]": {
                    "stat": 0.24876413682374407,
                    "syst": 0.0,
                    "value": 2.3103099281948234
                },
                "abseta:[2.1,2.4]": {
                    "stat": 1.0566815992703684,
                    "syst": 0.0,
                    "value": 4.44392221816937
                }
            }
        }
    }
}